joker_mongodb-0.5.0-py3.10-nspkg.pth
joker/mongodb/__init__.py
joker/mongodb/batch.py
joker/mongodb/candies.py
joker/mongodb/interfaces.py
joker/mongodb/legacy.py
joker/mongodb/logger.py
joker/mongodb/pagination.py
joker/mongodb/query.py
joker/mongodb/utils.py
joker/mongodb/aggregation/__init__.py
joker/mongodb/aggregation/lookup.py
joker/mongodb/aggregation/ops.py
joker/mongodb/tools/__init__.py
joker/mongodb/tools/cmdline.py
joker/mongodb/tools/dumping.py
joker/mongodb/tools/experimental.py
joker/mongodb/tools/integrity.py
joker/mongodb/tools/kvstore.py
joker/mongodb/tools/misc.py
joker/mongodb/tools/mongoshell.py
joker/mongodb/tools/oplog.py
joker/mongodb/tools/restore.py
joker/mongodb/tools/schema.py
joker_mongodb-0.5.0.dist-info/LICENSE
joker_mongodb-0.5.0.dist-info/METADATA
joker_mongodb-0.5.0.dist-info/WHEEL
joker_mongodb-0.5.0.dist-info/namespace_packages.txt
joker_mongodb-0.5.0.dist-info/top_level.txt
joker_mongodb-0.5.0.dist-info/RECORD
