Metadata-Version: 2.1
Name: joker-mongodb
Version: 0.5.0
Summary: access mongodb with handy utilities and fun
Home-page: https://github.com/frozflame/joker-mongodb
Author: frozflame
Author-email: frozflame@outlook.com
License: GNU General Public License (GPL)
Classifier: Programming Language :: Python
Classifier: Programming Language :: Python :: 3
Classifier: Programming Language :: Python :: 3.7
Classifier: Programming Language :: Python :: 3.8
Classifier: Programming Language :: Python :: 3.9
Classifier: Programming Language :: Python :: 3.10
Classifier: Programming Language :: Python :: 3.11
Classifier: Programming Language :: Python :: 3.12
Classifier: Programming Language :: Python :: 3.13
Requires-Python: >=3.7.0
License-File: LICENSE
Requires-Dist: joker-cast >=0.5.0
Requires-Dist: joker-textmanip >=0.3.1
Requires-Dist: joker >=0.3.3
Requires-Dist: pymongo >=3.11.0
Requires-Dist: requests >=2.0.0
Requires-Dist: volkanic >=0.5.1
